ldgm/__init__.py
ldgm/__main__.py
ldgm/brickhaplograph.py
ldgm/bricks.py
ldgm/cli.py
ldgm/core.py
ldgm/provenance.py
ldgm/reduction.py
ldgm/utility.py
ldgm-0.0.1.dist-info/METADATA
ldgm-0.0.1.dist-info/WHEEL
ldgm-0.0.1.dist-info/licenses/LICENSE
ldgm-0.0.1.dist-info/RECORD
