Metadata-Version: 2.1
Name: ldgm
Version: 0.0.1
Summary: Sparse and accurate modeling of linkage disequilibrium
Project-URL: Homepage, https://github.com/awohns/ldgm
Project-URL: Bug Tracker, https://github.com/awohns/ldgm/issues
Author-email: Anthony Wilder Wohns <awohns@gmail.com>, Luke O'Connor <loconnor@broadinstitute.org>, Pouria Salehi Nowbandegani <psalehin@broadinstitute.org>
License-File: LICENSE
Classifier: License :: OSI Approved :: MIT License
Classifier: Operating System :: OS Independent
Classifier: Programming Language :: Python :: 3
Requires-Python: >=3.7
